LICENSE
README.rst
setup.py
strinpy/__init__.py
strinpy/builder.py
strinpy.egg-info/PKG-INFO
strinpy.egg-info/SOURCES.txt
strinpy.egg-info/dependency_links.txt
strinpy.egg-info/top_level.txt