Metadata-Version: 2.1
Name: strinpy
Version: 0.0.1
Summary: React like string builder
Home-page: https://github.com/am230/strinpy
Author: am230
License: MIT Licence
Keywords: string
Platform: any
License-File: LICENSE
